aporia_importer/__init__.py
aporia_importer/config.py
aporia_importer/data_loader.py
aporia_importer/logging_utils.py
aporia_importer/main.py
aporia_importer-1.0.6.dist-info/entry_points.txt
aporia_importer-1.0.6.dist-info/LICENSE
aporia_importer-1.0.6.dist-info/WHEEL
aporia_importer-1.0.6.dist-info/METADATA
aporia_importer-1.0.6.dist-info/RECORD
