Metadata-Version: 2.1
Name: aporia-importer
Version: 1.0.6
Summary: Import data from cloud storage to Aporia
Home-page: https://github.com/aporia-ai/aporia-importer
Requires-Python: >=3.7,<4.0
Classifier: Programming Language :: Python :: 3
Classifier: Programming Language :: Python :: 3.7
Classifier: Programming Language :: Python :: 3.8
Classifier: Programming Language :: Python :: 3.9
Provides-Extra: all
Provides-Extra: s3
Requires-Dist: PyYAML (>=5.4.1,<6.0.0)
Requires-Dist: aporia[all] (>=1.0.59,<2.0.0)
Requires-Dist: dask[complete] (>=2021.6.0,<2022.0.0)
Requires-Dist: importlib-metadata (>=1.5.0,<2.0.0); python_version < "3.8"
Requires-Dist: s3fs (>=2021.6.0,<2022.0.0); extra == "s3" or extra == "all"
Project-URL: Repository, https://github.com/aporia-ai/aporia-importer
